Workbook

Sheet Sheet1
A1: EMU Park Administration | G1: Shift -1 8:00AM - 10:00AM
D2: Group 1 | E2: Group 2 | F2: Group 3 | G2: Group 4 | H2: Group 5
A3: Total No of People | D3: 10 | E3: 5 | F3: 8 | G3: 10 | H3: 15
A4: AVG Ticket Price | D4: 8 | E4: 8 | F4: 8 | G4: 8 | H4: 6
A5: Total Price Paid | D5: =D4*D3 -> 80 | E5: =E4*E3 -> 40 | F5: =F4*F3 -> 64 | G5: =G4*G3 -> 80 | H5: =H4*H3 -> 90
A6: Total Discount Given | D6: =IF(D3>=10,D3*2) -> 20 | E6: =IF(E4<=10,E3*2) -> 10 | F6: =IF(F4<=10,F3*2) -> 16 | G6: =IF(G4<=10,G3*2) -> 20 | H6: =IF(H4<=10,H3*4) -> 60
A13: Total No of People | D13: =D3+E3+F3+G3+H3 -> 48 | E13: =IF(D13>=50,"Warning: Limit Exceeded!!!","")
A14: Avg Ticket Price | D14: =AVERAGE(D4:H4) -> 7.6
A15: Total Revenue The Shift | D15: =D5+E5+F5+G5+H5 -> 354
A16: Total Discount Given | D16: =SUM(D6:H6) -> 126

Sheet Sheet2
A1: EMU Park Administration | G1: Shift -2 10:00AM - 12:00PM
D2: Group 1 | E2: Group 2 | F2: Group 3 | G2: Group 4 | H2: Group 5
A3: Total No of People | D3: 15 | E3: 5 | F3: 7 | G3: 9 | H3: 13
A4: AVG Ticket Price | D4: 6 | E4: 8 | F4: 8 | G4: 8 | H4: 6
A5: Total Price Paid | D5: =D4*D3 -> 90 | E5: =E4*E3 -> 40 | F5: =F4*F3 -> 56 | G5: =G4*G3 -> 72 | H5: =H4*H3 -> 78
A6: Total Discount Given | D6: =IF(D3>=10,D3*2) -> 30 | E6: =IF(E4<=10,E3*2) -> 10 | F6: =IF(F4<=10,F3*2) -> 14 | G6: =IF(G4<=10,G3*2) -> 18 | H6: =IF(H4<=10,H3*4) -> 52
A13: Total No of People | D13: =D3+E3+F3+G3+H3 -> 49 | F13: =IF(D13>=50,"Warning: Limit Exceeded!!!","")
A14: Avg Ticket Price | D14: =AVERAGE(D4:H4) -> 7.2
A15: Total Revenue The Shift | D15: =D5+E5+F5+G5+H5 -> 336
A16: Total Discount Given | D16: =SUM(D6:H6) -> 124

Sheet Sheet3
A1: EMU Park Administration | G1: Shift -2 1:00PM - 3:00PM
D2: Group 1 | E2: Group 2 | F2: Group 3 | G2: Group 4 | H2: Group 5
A3: Total No of People | D3: 15 | E3: 15 | F3: 0 | G3: 0 | H3: 18
A4: AVG Ticket Price | D4: 6 | E4: 6 | F4: 0 | G4: 0 | H4: 6
A5: Total Price Paid | D5: =D4*D3 -> 90 | E5: =E4*E3 -> 90 | F5: =F4*F3 -> 0 | G5: =G4*G3 -> 0 | H5: =H4*H3 -> 108
A6: Total Discount Given | D6: =IF(D3>=10,D3*2) -> 30 | E6: =IF(E4<=10,E3*2) -> 30 | F6: =IF(F4<=10,F3*2) -> 0 | G6: =IF(G4<=10,G3*2) -> 0 | H6: =IF(H4<=10,H3*4) -> 72
A13: Total No of People | D13: =SUM(D3:H3) -> 48 | F13: =IF(D13>=50,"Warning: Limit Exceeded!!!","")
A14: Avg Ticket Price | D14: =AVERAGE(D4:H4) -> 3.6
A15: Total Revenue The Shift | D15: =D5+E5+F5+G5+H5 -> 288
A16: Total Discount Given | D16: =SUM(D6:H6) -> 132

Sheet Sheet4
A1: EMU Park Administration | G1: Shift -2 3:00PM - 5:00PM
D2: Group 1 | E2: Group 2 | F2: Group 3 | G2: Group 4 | H2: Group 5
A3: Total No of People | D3: 10 | E3: 10 | F3: 10 | G3: 10 | H3: 2
A4: AVG Ticket Price | D4: 6 | E4: 6 | F4: 6 | G4: 6 | H4: 10
A5: Total Price Paid | D5: =D3*D4 -> 60 | E5: =E3*E4 -> 60 | F5: =F3*F4 -> 60 | G5: =G3*G4 -> 60 | H5: =H3*H4 -> 20
A6: Total Discount Given | D6: 30 | E6: 10 | F6: 14 | G6: 18 | H6: 60
A13: Total No of People | D13: =SUM(D3:H3) -> 42 | F13: Warning: Limit Exceeded!!!
A14: Avg Ticket Price | D14: =AVERAGE(D4:H4) -> 6.8
A15: Total Revenue The Shift | D15: =SUM(D5:H5) -> 260
A16: Total Discount Given | D16: =SUM(D6:H6) -> 132

Sheet Total Sales
G1: Emu Park Daily Sales Report
D4: Shift - 1 | F4: Shift - 2 | H4: Shift - 3 | J4: Shift - 4
A6: Total No of People | D6: =SUM(Sheet1!D3:H3) -> 48 | F6: =SUM(Sheet2!D3:H3) -> 49 | H6: =SUM(Sheet3!D3:H3) -> 48 | J6: =SUM(Sheet4!D3:H3) -> 42
A7: AVG Ticket Price | D7: =AVERAGE(Sheet1!D4:H4) -> 7.6 | F7: =AVERAGE(Sheet2!D4:H4) -> 7.2 | H7: =AVERAGE(Sheet3!D4:H4) -> 3.6 | J7: =AVERAGE(Sheet4!D4:H4) -> 6.8
A8: Total Price Paid | D8: =SUM(Sheet1!D5:H5) -> 354 | F8: =SUM(Sheet2!D5:H5) -> 336 | H8: =SUM(Sheet3!D5:H5) -> 288 | J8: =SUM(Sheet4!D5:H5) -> 260
A9: Total Discount Given | D9: =SUM(Sheet1!D6:H6) -> 126 | F9: =SUM(Sheet2!D6:H6) -> 124 | H9: =SUM(Sheet3!D6:H6) -> 132 | J9: =SUM(Sheet4!D6:H6) -> 132
B13: Total Summary of The Day
A15: Total No of People | D15: =SUM(D6+F6+H6+J6) -> 187
A16: Avg Ticket Price | D16: =AVERAGE(D7,F7,H7,J7) -> 6.3
A17: Total Revenue in The Shift | D17: =SUM(D8,F8,H8,J8) -> 1238
A18: Total Discount Given | D18: =SUM(D9,F9,H9,J9) -> 514
